shapley_decomposition/__init__.py
shapley_decomposition/shapley_change.py
shapley_decomposition/shapley_r2.py
shapley_decomposition/shared_tools.py
tests/__init__.py
tests/test_r2decomp.py
tests/test_shapleychange.py
tests/test_sharedtools.py
shapley_decomposition-0.0.2.dist-info/LICENSE.txt
shapley_decomposition-0.0.2.dist-info/METADATA
shapley_decomposition-0.0.2.dist-info/WHEEL
shapley_decomposition-0.0.2.dist-info/top_level.txt
shapley_decomposition-0.0.2.dist-info/RECORD
