Metadata-Version: 2.1
Name: shapley-decomposition
Version: 0.0.2
Summary: Decomposition using shapley values
Home-page: https://github.com/canitez01/shapley_decomposition
Author: Can Itez
Author-email: <canitez01@hotmail.com>
License: MIT
Keywords: python,data analysis,descriptive analysis,shapley values,owen values,decomposition
Classifier: Development Status :: 4 - Beta
Classifier: Intended Audience :: Science/Research
Classifier: Programming Language :: Python :: 3
Classifier: Programming Language :: Python :: 3.6
Classifier: Programming Language :: Python :: 3.7
Classifier: Programming Language :: Python :: 3.8
Classifier: Programming Language :: Python :: 3.9
Classifier: Programming Language :: Python :: 3.10
Classifier: Programming Language :: Python :: 3.11
Classifier: License :: OSI Approved :: MIT License
Classifier: Operating System :: OS Independent
License-File: LICENSE.txt
Requires-Dist: pandas>=1.1
Requires-Dist: numpy>=1.3
Requires-Dist: scikit-learn>=0.24
Provides-Extra: dev
Requires-Dist: pytest>=6.2.4; extra == "dev"
